{"cameraMode":{"drawMode":0,"name":"Shaded","section":"Shading Mode"},"sceneLighting":false,"audioPlay":false,"sceneViewState":{"m_AlwaysRefresh":false,"showFog":true,"showSkybox":false,"showFlares":true,"showImageEffects":true,"showParticleSystems":true,"showVisualEffectGraphs":true,"m_FxEnabled":true},"in2DMode":false,"pivot":{"x":-0.01382405310869217,"y":0.016906701028347017,"z":-0.012804124504327774},"rotation":{"x":0.22489605844020844,"y":-0.7497715950012207,"z":0.31373992562294009,"w":0.5374460816383362},"size":0.053486473858356479,"orthographic":false}